<?xml version="1.0" encoding="windows-1250"?>
<string_table>

<string id="st_soulslike_rescuers_radio_frequency_note_name">
    <text>Poznámka Zachránce</text>
</string>

<string id="st_soulslike_rescuers_radio_frequency_note_desc">
    <text>Poznámka napsaná jedním z Stalkerù, kteøí tì zachránili.</text>
</string>

<string id="st_soulslike_rescuers_radio_frequency_note_message">
    <text>Tato poznámka obsahuje informace o tom, kde jsou tvé vìci. Øíká, že použij RF pøijímaè s frekvencí %s v %s</text>
</string>


</string_table>