<?xml version="1.0" encoding="windows-1250"?>

<string_table>

<!--

	MCM

-->
	<string id="ui_mcm_menu_experience_framework">
		<text>Nastavení Dovedností</text>
	</string>
	<string id="ui_mcm_experience_framework_DISPLAY_UI">
		<text>Menu Dovedností</text>
	</string>
	<string id="ui_mcm_experience_framework_DISPLAY_UI_desc">
		<text>Keybindy</text>
	</string>
	<string id="ui_mcm_experience_framework_KEY_MODIFIER">
		<text>Dodateènı keybind</text>
	</string>
<string id="ui_mcm_lst_experience_framework_KEY_MODIFIER_none">
    <text>ádnı</text>
</string>
<string id="ui_mcm_lst_experience_framework_KEY_MODIFIER_shift">
    <text>Shift</text>
</string>
<string id="ui_mcm_lst_experience_framework_KEY_MODIFIER_ctrl">
    <text>Ctrl</text>
</string>
<string id="ui_mcm_lst_experience_framework_KEY_MODIFIER_alt">
    <text>Alt</text>
</string>
<string id="ui_mcm_experience_framework_KEY_MODE">
    <text>Reim stisknutí</text>
</string>
<string id="ui_mcm_lst_experience_framework_KEY_MODE_press">
    <text>Jednoduché</text>
</string>
<string id="ui_mcm_lst_experience_framework_KEY_MODE_dtap">
    <text>Dvojité</text>
</string>


<!--

	Options Info

-->
	<string id="ui_exp_menu_Info">
    <text>Info</text>
</string>

<string id="ui_exp_menu_AboutFramework">
    <text>O modifikaci</text>
</string>

<string id="ui_exp_Info_AboutFramework_title">
    <text>EXPERIENCE FRAMEWORK 2.0</text>
</string>

<string id="ui_exp_Info_AboutFramework_desc">
    <text>
    Experience Framework je modifikace pro S.T.A.L.K.E.R. - Anomaly, jejím cílem je vytvoøit systém postupování postavy a další mechaniky, které existují v jinıch RPG hrách.
    \n
    \nAnomaly je pøedevším hra pro jednoho hráèe, take máte jako hráè právo zvolit si svùj vlastní herní styl, a proto zde v této modifikaci existuje mnoho rùznıch nastavení, která mùete bezpeènì upravit podle svého uváení a pøizpùsobit si tak fungování Experience Framework pro sebe!
    \n
    \nPokud chcete nahlásit chybu nebo vyjádøit svá pøání èi nápady, mùete to udìlat na oficiální stránce módu na ModDB nebo v Discordu: @Orleon.
    \n
    \nChcete-li se dozvìdìt více o nìkterıch aspektech této modifikace, podívejte se na následující sekce.
    </text>
</string>

<string id="ui_exp_menu_AboutExperience">
    <text>Postup</text>
</string>

<string id="ui_exp_Info_AboutExperience_title">
    <text>Systém postupování postavy</text>
</string>

<string id="ui_exp_Info_AboutExperience_desc">
    <text>
    Chcete-li postupovat svoji postavu, potøebujete získat zkušenosti. Zkušenosti mùete získat za rùzné akce, a u jde o zabíjení dalších stalkerù èi mutantù, hledání artefaktù, opravu vybavení atd.
    \n
    \nZískáváním zkušeností zvyšujete úroveò své postavy. Zvıšení úrovnì vám poskytuje dovednostní body, které mùete pouít k nauèení se dovedností (o dovednostech se dozvíte níe). Jakmile dosáhnete maximální úrovnì, budete moci zvıšit prestiní úroveò, ale veškerı váš pokrok bude vynulován.
    \n
    \nZvyšováním prestie:
    \n - Zvyšujete maximální úroveò
    \n - Získáváte pøístup k dalším dovednostem
    \n - Zvyšuje se doba trvání lektvarù a pravdìpodobnost jejich nalezení (o lektvarech se dozvíte níe)
    \n - Zvyšuje se poèet dostupnıch úkolù, jejich obtínost a odmìna za jejich dokonèení (o úkolech se dozvíte níe)
    \n
    \nPresti je volitelná mechanika, take její zvıšení není nezbytné.
    </text>
</string>

<string id="ui_exp_menu_AboutSkills">
    <text>Dovednosti</text>
</string>

<string id="ui_exp_Info_AboutSkills_title">
    <text>Systém dovedností</text>
</string>

<string id="ui_exp_Info_AboutSkills_desc">
    <text>
    Kadá dovednost je rozdìlena na úrovnì. Uèením se úrovnì dovednosti utratíte jeden dovednostní bod a získáte vlastnosti uvedené v jejím popisu. Kadá úroveò dovednosti má poadavek na úroveò postavy a presti, pøi kterıch je její uèení dostupné.
    \n
    \nPokud znáte programovací jazyk Lua a rozumíte se modifikování hry Stalker, mùete snadno pøidat svou vlastní dovednost. Jak na to, mùete zjistit na oficiální stránce módu na ModDB.
    \n
    \nV základním nastavení Experience Framework neobsahuje ádné dovednosti.
    </text>
</string>

	
<string id="ui_exp_menu_AboutPotions">
    <text>Lektvary</text>
</string>

<string id="ui_exp_Info_AboutPotions_title">
    <text>Lektvary a jak je získat</text>
</string>

<string id="ui_exp_Info_AboutPotions_desc">
    <text>
    Existují dva druhy lektvarù:
    \n - Vìdeckı lektvar - Doèasnì zvyšuje mnoství získanıch zkušeností ze všech zdrojù
    \n - Lektvary Zapomnìní - Umoòují vám zapomenout na nauèené dovednosti a vrátit body utracené za nì, pøièem po dobu trvání penalty dojde ke sníení získanıch zkušeností, neschopnosti pouívat jiné lektvary a opakovanému pouití tohoto lektvaru bìhem doby trestu hráèe zabije.
    \n
    \nLektvary lze najít s urèitou šancí na tìlech mrtvıch stalkerù, nìkterıch mutantù nebo ve skrıších.
    </text>
</string>

<string id="ui_exp_menu_AboutTasks">
    <text>Úkoly</text>
</string>

<string id="ui_exp_Info_AboutTasks_title">
    <text>Systém úkolù</text>
</string>

<string id="ui_exp_Info_AboutTasks_desc">
    <text>
    Úkoly vám umoní získat dodateèné peníze nebo zkušenosti. Seznam úkolù se prùbìnì aktualizuje.
    \n
    \nPoznámka: Kadá úroveò prestie zvyšuje poèet úkolù, jejich obtínost a odmìnu za jejich dokonèení.
    </text>
</string>

<string id="ui_exp_menu_AboutNLS">
    <text>System NLS</text>
</string>

<string id="ui_exp_Info_AboutNLS_title">
    <text>Systém postupování NPC</text>
</string>

<string id="ui_exp_Info_AboutNLS_desc">
    <text>
    Systém postupování NPC dává všem stalkerùm a mutantùm systém postupování stejnì jako hráèi, ale ve zjednodušené podobì.
    \n
    \nProces vytvoøení NPC:
    \n - Kdy se NPC objeví na urèitém místì, je mu náhodnì pøidìlena úroveò, která závisí na samotném místì. Mùete zmìnit povolené limity minimální a maximální úrovnì v nastavení "NLS".
    \n
    \nZískané zkušenosti NPC:
    \n - Vìtšina NPC získává zkušenosti pouze za vzájemné zabíjení, take se postupují tøikrát rychleji ne hráè (monost "Globální multiplikátor zkušeností" je násobena tøemi). K tomu je zkušeností získanıch NPC za zabíjení násobena "Multiplikátorem úrovnì" (o multiplikátoru úrovnì viz sekce "Multiplikátory").
    \n
    \nZvyšování úrovnì NPC:
    \n - NPC stoupají na úrovni stejnì jako hráè, ale navíc jsou zcela uzdraveni. Maximální moná úroveò NPC je vdy stejná jako maximální úroveò hráèe.
    \n
    \nVliv NPC na hráèe:
    \n - V základním nastavení se NPC a jejich úroveò vùbec nedotıkají hráèe, ale mùete to zmìnit pøejít do nastavení "NLS". V nastavení mùete zapnout multiplikátor zkušeností za zabíjení pro hráèe, kterı zvıší nebo sníí základní získané zkušenosti za zabíjení v závislosti na rozdílu úrovní mezi hráèem a zabitém nepøítelem. V nastavení je také monost zapnout multiplikátor poškození pro NPC a hráèe, kterı také buï zvıší nebo sníí poškození v závislosti na rozdílu úrovní mezi NPC a hráèem, a mùete také zapnout cílovı HUD, kterı vám umoní vidìt zdraví NPC a jejich úroveò.
    </text>
</string>

<string id="ui_exp_menu_AboutTraits">
    <text>Traity</text>
</string>
<string id="ui_exp_Info_AboutTraits_title">
    <text>Systém traitù</text>
</string>
<string id="ui_exp_Info_AboutTraits_desc">
    <text>
        Systém traitù je mechanismus, kterı vám umoòuje posílit svou postavu speciálními pøedmìty (vlastnostmi).\n
        \nPøi prùzkumu Zóny narazíte na pøedmìty, u kterıch je ve popisu poznámka "Pøi sebraní pøedmìt zablokován". Kdy takovı pøedmìt seberete, pøidá se do inventáøe v menu traitù.
        \nKadá vlastnost má úroveò ostøení a úroveò kvality. Kdy je vlastnost nalezena, nebude ostøena, ale bude mít náhodnou úroveò kvality.
        \nPOZNÁMKA: Šance na nalezení vlastnosti lepší kvality se zvyšuje s úrovní prestie (maximální šance je na 4. úrovni).\n
        \nPro aktivaci vlastnosti ji musíte umístit do speciálních slotù v menu traitù (Pro umístìní vlastnosti do slotu ji pøetáhnìte z inventáøe, podrte levé tlaèítko myši a pro uvolnìní slotu dvakrát klepnìte na nìj). Avšak pro aktivaci vlastnosti musíte zvıšit její úroveò ostøení alespoò na +1.
        \nOstatní vlastnosti slouí k zvıšení úrovnì ostøení. Nejprve vyberte poadovanou vlastnost a poté kliknìte na "Upgrade" v pravém dolním rohu. Uvidíte další inventáø, ve kterém musíte vybrat vlastnost, kterou chcete pouít k vylepšení. Zvıšení úrovnì ostøení má šanci na úspìšné ostøení, která závisí na aktuální úrovni ostøení a kvalitì vlastnosti "upgradované" a "vybrané k upgradu". Pøi ostøení bude vlastnost "vybraná k upgradu" znièena!
        \nPoté, co ostøíte vlastnost na maximální úroveò, mùete zvıšit její úroveò kvality.
        \nExistuje sedm úrovní kvality:
        \n %c[255,210,20,20]- Hrozná
        \n %c[255,205,205,205]- Špatná
        \n %c[255,100,220,140]- Bìná
        \n %c[255,35,110,175]- Dobrá
        \n %c[255,180,65,240]- Epická
        \n %c[255,240,195,40]- Legendární
        \n %c[255,240,100,40]- Mystická
        \n%c[default]Zvyšováním úrovnì kvality se zvyšují efekty, které lze získat z vlastnosti pro kadou úroveò ostøení. Avšak úroveò ostøení klesne na +1.\n
        \nPOZNÁMKA: Zbyteèné vlastnosti lze znièit za zkušenosti.
    </text>
</string>

	
<string id="ui_exp_menu_AboutMultipliers">
    <text>Multiplikátory</text>
</string>

<string id="ui_exp_Info_AboutMultipliers_title">
    <text>Všechny multiplikátory zkušeností</text>
</string>

<string id="ui_exp_Info_AboutMultipliers_desc">
    <text>
    "Globální multiplikátor" - hlavní multiplikátor zkušeností hráèe a NPC (ale v trojnásobné velikosti). Jeho nastavení se nachází v sekci "Hlavní".
    \n
    \n"Multiplikátor lektvarù" - multiplikátor zkušeností, kterı lze získat pouitím lektvarù. Ovlivòuje pouze hráèe.
    \n
    \n"Multiplikátory podle lokací" - multiplikátory zkušeností závislé na lokaci, ve které se hráè nachází. Nastavení naleznete v sekci "XP". Ovlivòují pouze hráèe.
    \n
    \n"Multiplikátory akcí" - multiplikátory zkušeností hráèe za rùzné akce. Aktuální hodnoty multiplikátorù mùete zobrazit v nabídce "Multiplikátory zkušeností".
    \n
    \n"Multiplikátory podle hodnosti" - multiplikátory zkušeností, které pøedevším násobí základní zkušenost za zabíjení nepøítele v závislosti na jeho hodnosti. Ovlivòují pouze hráèe.
    \n
    \n"Multiplikátor asistence pøi zabíjení" - skrytı multiplikátor zkušeností za zabití. Pokud nepøítel zemøe do 20 sekund od posledního zpùsobeného poškození, ale poslední zásah nebyl udìlen hráèem, získaná zkušenost bude sníena na polovinu.
    \n
    \n"Multiplikátor úrovnì" - unikátní multiplikátor pro NPC tıkající se poškození/získaného poškození a zkušeností za zabití. Hodnota multiplikátoru se mìní v závislosti na rozdílu úrovní mezi NPC nahoru nebo dolù. Práh rozdílu úrovní a další nastavení související s multiplikátorem úrovnì se nacházejí v sekci "NLS". Tento multiplikátor mùe bıt také aktivován pro hráèe. Pokud aktivujete multiplikátor úrovnì zkušeností pro hráèe za zabíjení, bude fungovat pouze tehdy, pokud nepøítel zemøe na rukou hráèe (ne od spoleèníka). Kdy multiplikátor úrovnì zkušeností funguje pro hráèe, "Multiplikátory podle hodnosti" budou ignorovány. Pokud aktivujete multiplikátor poškození podle úrovnì pro NPC a hráèe, všichni NPC i hráèi budou udìlovat a pøijímat poškození na základì rozdílu jejich úrovní.
    \n
    \n"Multiplikátor úkolù dìjové linky" - multiplikátor, kterı pøedevším násobí základní zkušenost za dokonèení úkolu, pokud byl souèástí dìjové linky. Nastavení naleznete v sekci "XP".
    \n
    \n"Multiplikátory artefaktù" - multiplikátory, které pøedevším násobí základní zkušenost za nalezení artefaktu, v závislosti na jeho hodnosti. Nastavení naleznete v sekci "XP".
    </text>
</string>

<string id="ui_exp_menu_DeleteMod">
    <text>Odstranìní</text>
</string>

<string id="ui_exp_Info_DeleteMod_desc">
    <text>
    Pokud chcete modifikaci bezpeènì odstranit, kliknìte na tlaèítko níe a spuste proces odstranìní dat. Po dokonèení bude vytvoøeno nové uloení a hra se zavøe, take se neplašte. Po zavøení hry odstraòte všechny soubory související s modifikací z koøenového adresáøe hry, èím dokonèíte proces bezpeèného odstranìní modifikace!
    \n
    \nPo odstranìní pouijte automaticky vytvoøené uloení, které vzniklo bìhem procesu odstranìní.
    \n
    \nV SOUÈASNÉ HERNÍ RELACI BUDE ODSTRANÌNO:
    \n - Všechny poloky související s modifikací budou odstranìny ze svìta.
    \n - Všechna uloená data související s modifikací.
    </text>
</string>

<string id="ui_exp_Info_DeleteMod_DELETE_MOD">
    <text>Odstranit Experience Framework</text>
</string>



<!--

	Options Main

-->
	<string id="ui_exp_menu_Main">
    <text>Hlavní</text>
</string>

<string id="ui_exp_Main_title">
    <text>Hlavní Nastavení</text>
</string>

<string id="ui_exp_Main_G_MAX_LEVEL">
    <text>Maximální Základní Úroveò</text>
</string>

<string id="ui_exp_Main_G_MAX_LEVEL_desc">
    <text>(Toto nastavení ovlivòuje také NPC)</text>
</string>

<string id="ui_exp_Main_G_SKILLPOINT_PER_LEVEL">
    <text>Dovednostní Body na Úroveò</text>
</string>

<string id="ui_exp_Main_G_MAX_PRESTIGE">
    <text>Maximální Prestiní Úroveò</text>
</string>

<string id="ui_exp_Main_G_ADD_LEVEL_PER_PRESTIGE">
    <text>Pøidat Úrovnì za Presti</text>
</string>

<string id="ui_exp_Main_GLOBAL_EXPERIENCE_MULT">
    <text>Globální Multiplikátor Zkušeností</text>
</string>

<string id="ui_exp_Main_GLOBAL_EXPERIENCE_MULT_desc">
    <text>(Toto nastavení ovlivòuje také NPC) \n \nToto nastavení upravuje multiplikátor pro získávání zkušeností ze všech zdrojù.</text>
</string>

<string id="ui_exp_Main_CAN_SPAWN_POTIONS">
    <text>Povolit Vytváøení Lektvarù</text>
</string>

<string id="ui_exp_Main_AZAZEL_NEW_PROGRESS">
    <text>Azazel: Novı Pokrok</text>
</string>

<string id="ui_exp_Main_AZAZEL_NEW_PROGRESS_desc">
    <text>Zkopíruje postup postupu NPC, do kterého hráè bude respawnován pøi hraní v reimu "Azazel". \n \nPOZNÁMKA: Pokud NPC není registrováno v systému "NLS", bude pro hráèe vygenerován náhodnı postup.</text>
</string>


	<string id="ui_exp_Main_traits_system_title">
		<text>Systém traitù</text>
	</string>
	<string id="ui_exp_Main_MAX_SPAWN_TRAITS">
		<text>Max. mnoství traitù</text>
	</string>
	<string id="ui_exp_Main_MAX_SPAWN_TRAITS_desc">
		<text>Maximální poèet traitù, které mohou bıt najednou spawnovány (od "nula" do "volitelná hodnota")</text>.
	</string>
	<string id="ui_exp_Main_TRAITS_SPAWN_CHANCE_stash">
		<text>Šance na spawnování traitù (skrıše)</text>
	</string>
	<string id="ui_exp_Main_TRAITS_SPAWN_CHANCE_stalker">
		<text>Maximalní šance na spawn traitù (stalkeøi)</text>
	</string>
	<string id="ui_exp_Main_TRAITS_SPAWN_CHANCE_mutant">
		<text>Maximalní šance na spawn traitù (mutanti)</text>
	</string>


<string id="ui_exp_Main_xp_comp_desc">
    <text>
    Následující nastavení ovlivòují, o kolik se sníí základní zkušenost, kterou získáte, kdy vaši spoleèníci zabíjí nepøátele, v závislosti na jejich poètu ve vašem tımu.
    \nPokud je monost zakázána, vaši spoleèníci vám pøinesou plnou zkušenost za zabíjení. \n 
    \nPOZNÁMKA: Minimální práh zkušeností, kterı obdríte v pøípadech, kdy máte pøíliš mnoho spoleèníkù, je 5 % základní zkušenosti.
    </text>
</string>

<string id="ui_exp_Main_ENABLE_COMP_XP">
    <text>Povolit vliv spoleèníkù na XP</text>
</string>

<string id="ui_exp_Main_REDUCE_COMP_XP">
    <text>Sníení XP (za kadého spoleèníka)</text>
</string>

<string id="ui_exp_Main_UNLOCK_CONSOLE">
    <text>Odemknout konzolové menu</text>
</string>


<!--

	Options XP

-->
	<string id="ui_exp_menu_XP">
		<text>XP</text>
	</string>
	<string id="ui_exp_XP_title">
    <text>Nastavení Zkušeností</text>
</string>

<string id="ui_exp_XP_xps_level_up_descr">
    <text>
    Dvì nastavení níe ovlivòují mnoství zkušeností potøebnıch pro postup na vyšší úroveò a pøímo ovlivòují, jak rychle se váš postava bude levelovat!\n
    \nDÙLEITÉ!!! Vıpoèet zkušeností pro následující úroveò probíhá pouze tehdy, kdy dosáhnete nové úrovnì!\n
    \nXP_LEVEL_UP_BASE je základní zkušenost potøebná pro postup na kadou úroveò. \nXP_LEVEL_UP_MULT je multiplikátor zkušeností, kterı se násobí s novì dosaenou úrovní.\n
    \nVİPOÈET ZKUŠENOSTÍ: XP_LEVEL_UP_BASE + AKTUÁLNÍ ÚROVEÒ * XP_LEVEL_UP_MULT\n
    \nPOZNÁMKA: Tato nastavení také ovlivòují NPC.
    </text>
</string>

<string id="ui_exp_XP_LEVEL_UP_BASE">
    <text>XP_LEVEL_UP_BASE</text>
</string>

<string id="ui_exp_XP_LEVEL_UP_MULT">
    <text>XP_LEVEL_UP_MULT</text>
</string>

<string id="ui_exp_XP_stalkers_xp_title">
    <text>Základní zkušenosti za zabití stalkerù (Tato nastavení také ovlivòují NPC)</text>
</string>

<string id="ui_exp_XP_stalker">
    <text>Samotáø</text>
</string>

<string id="ui_exp_XP_bandit">
    <text>Bandita</text>
</string>

<string id="ui_exp_XP_csky">
    <text>Jasná obloha</text>
</string>

<string id="ui_exp_XP_army">
    <text>Armáda</text>
</string>

<string id="ui_exp_XP_freedom">
    <text>Svoboda</text>
</string>

<string id="ui_exp_XP_dolg">
    <text>Povinnost</text>
</string>

<string id="ui_exp_XP_ecolog">
    <text>Ekologové</text>
</string>

<string id="ui_exp_XP_killer">
    <text>oldáci</text>
</string>

<string id="ui_exp_XP_monolith">
    <text>Monolit</text>
</string>

<string id="ui_exp_XP_greh">
    <text>Høích</text>
</string>

<string id="ui_exp_XP_renegade">
    <text>Odpadlíci</text>
</string>

<string id="ui_exp_XP_isg">
    <text>UNISG</text>
</string>

<string id="ui_exp_XP_zombied">
    <text>Zombifikovanı</text>
</string>

	
	<string id="ui_exp_XP_stalkers_rank_mult_title">
    <text>Multiplikátory zkušeností podle hodnosti pro zabíjení stalkerù</text>
</string>

<string id="ui_exp_XP_novice">
    <text>Nováèek</text>
</string>

<string id="ui_exp_XP_trainee">
    <text>Uèeò</text>
</string>

<string id="ui_exp_XP_experienced">
    <text>Zkušenı</text>
</string>

<string id="ui_exp_XP_professional">
    <text>Profesionál</text>
</string>

<string id="ui_exp_XP_veteran">
    <text>Veterán</text>
</string>

<string id="ui_exp_XP_expert">
    <text>Expert</text>
</string>

<string id="ui_exp_XP_master">
    <text>Mistr</text>
</string>

<string id="ui_exp_XP_legend">
    <text>Legenda</text>
</string>

<string id="ui_exp_XP_mutants_xp_title">
    <text>Základní zkušenosti za zabíjení mutantù (Tato nastavení také ovlivòují NPC)</text>
</string>

<string id="ui_exp_XP_bloodsucker">
    <text>Upír</text>
</string>

<string id="ui_exp_XP_boar">
    <text>Divoèák</text>
</string>

<string id="ui_exp_XP_burer">
    <text>Trpaslík</text>
</string>

<string id="ui_exp_XP_chimera">
    <text>Chiméra</text>
</string>

<string id="ui_exp_XP_controller">
    <text>Kontrolér</text>
</string>

<string id="ui_exp_XP_dog">
    <text>Slepı pes</text>
</string>

<string id="ui_exp_XP_flesh">
    <text>Flaksa</text>
</string>

<string id="ui_exp_XP_gigant">
    <text>Pseudogiant</text>
</string>

<string id="ui_exp_XP_poltergeist">
    <text>Poltergeist</text>
</string>

<string id="ui_exp_XP_pyrogeist">
    <text>Pyrogeist</text>
</string>

<string id="ui_exp_XP_pseudogeist">
    <text>Pseudogeist</text>
</string>

<string id="ui_exp_XP_psy_dog">
    <text>Psy-pes</text>
</string>

<string id="ui_exp_XP_pseudodog">
    <text>Pseudopes</text>
</string>

<string id="ui_exp_XP_snork">
    <text>Snork</text>
</string>

<string id="ui_exp_XP_tushkano">
    <text>Tarbík</text>
</string>

<string id="ui_exp_XP_cat">
    <text>Koèka</text>
</string>

<string id="ui_exp_XP_fracture">
    <text>Izlom</text>
</string>

<string id="ui_exp_XP_zombie">
    <text>Zombie</text>
</string>

<string id="ui_exp_XP_karlik">
    <text>Karlik</text>
</string>

<string id="ui_exp_XP_psysucker">
    <text>Psysucker</text>
</string>

<string id="ui_exp_XP_lurker">
    <text>Skrytı</text>
</string>

	
	<string id="ui_exp_XP_mutants_rank_mult_title">
    <text>Multiplikátory zkušeností podle hodnosti pro zabíjení mutantù</text>
</string>

<string id="ui_exp_XP_weak">
    <text>Slabı</text>
</string>

<string id="ui_exp_XP_normal">
    <text>Normální</text>
</string>

<string id="ui_exp_XP_strong">
    <text>Silnı</text>
</string>

<string id="ui_exp_XP_task_xp_title">
    <text>Základní zkušenosti za dokonèení úkolù</text>
</string>

<string id="ui_exp_XP_TASK_XP">
    <text>XP</text>
</string>

<string id="ui_exp_XP_TASK_XP_MULT">
    <text>Multiplikátor pøíbìhovıch úkolù</text>
</string>

<string id="ui_exp_XP_stash_xp_title">
    <text>Základní zkušenosti za nalezení úkrytu</text>
</string>

<string id="ui_exp_XP_STASH_XP">
    <text>XP</text>
</string>

<string id="ui_exp_XP_discover_spot_xp_title">
    <text>Základní zkušenosti za objevené místo</text>
</string>

<string id="ui_exp_XP_DISCOVER_SPOT_XP">
    <text>XP</text>
</string>

<string id="ui_exp_XP_disassembly_xp_title">
    <text>Základní zkušenosti za rozmontování pøedmìtù</text>
</string>

<string id="ui_exp_XP_DISASSEMBLY_WPN_XP">
    <text>XP za zbranì</text>
</string>

<string id="ui_exp_XP_DISASSEMBLY_OUT_XP">
    <text>XP za brnìní</text>
</string>

<string id="ui_exp_XP_DISASSEMBLY_ITM_XP">
    <text>XP za ostatní pøedmìty</text>
</string>

<string id="ui_exp_XP_mutant_loot_xp_title">
    <text>Základní zkušenosti za odkoení mutantù (Toto nastavení také ovlivòuje NPC)</text>
</string>

<string id="ui_exp_XP_MUTANT_LOOT_XP">
    <text>XP</text>
</string>

<string id="ui_exp_XP_repair_xp_title">
    <text>Základní zkušenosti za opravu pøedmìtù</text>
</string>

<string id="ui_exp_XP_repair_xp_descr">
    <text>POZNÁMKA: Základní zkušenosti * celkovı procentuální opravy</text>
</string>

<string id="ui_exp_XP_REPAIR_ITM_XP">
    <text>XP</text>
</string>

<string id="ui_exp_XP_cooking_xp_title">
    <text>Základní zkušenosti za vaøení</text>
</string>

<string id="ui_exp_XP_COOKING_XP">
    <text>XP</text>
</string>

<string id="ui_exp_XP_workshop_xp_title">
    <text>Základní zkušenosti za práci na pracovním stole</text>
</string>

<string id="ui_exp_XP_WORKSHOP_CRAFT_XP">
    <text>XP za vırobu</text>
</string>

<string id="ui_exp_XP_WORKSHOP_REPAIR_XP">
    <text>XP za opravu</text>
</string>

<string id="ui_exp_XP_WORKSHOP_UPGRADE_XP">
    <text>XP za vylepšení</text>
</string>

<string id="ui_exp_XP_art_xp_title">
    <text>Základní zkušenosti za nalezení artefaktù</text>
</string>

<string id="ui_exp_XP_ART_XP">
    <text>XP (Ovlivòuje NPC)</text>
</string>

<string id="ui_exp_XP_ART_XP_MULT_RANK_0">
    <text>Multiplikátor pro 0. hodnost (šrot)</text>
</string>

<string id="ui_exp_XP_ART_XP_MULT_RANK_1">
    <text>Multiplikátor pro 1. hodnost</text>
</string>

<string id="ui_exp_XP_ART_XP_MULT_RANK_2">
    <text>Multiplikátor pro 2. hodnost</text>
</string>

<string id="ui_exp_XP_ART_XP_MULT_RANK_3">
    <text>Multiplikátor pro 3. hodnost</text>
</string>

<string id="ui_exp_XP_haru_skills_xp_title">
    <text>Základní zkušenosti za uèení dovedností z modu "Anomaly Skill System"</text>
</string>

<string id="ui_exp_XP_haru_skills_xp_descr">
    <text>POZNÁMKA: Základní zkušenosti * nová získaná úroveò</text>
</string>

<string id="ui_exp_XP_HARU_SKILLS_XP">
    <text>XP</text>
</string>

<string id="ui_exp_XP_location_xp_mult_title">
    <text>Multiplikátor zkušeností za místa</text>
</string>

<string id="ui_exp_XP_location_xp_mult_descr">
    <text>Nastavení níe zmìní koneènou hodnotu multiplikátoru zkušeností, kdy je poèítán v závislosti na vaší poloze v Zónì. \nPØÍKLAD: Hodnota -0,3 je rovna -30% zkušeností.</text>
</string>



<!--

	Options UI

-->
	<string id="ui_exp_menu_UI">
    <text>Uivatelské rozhraní</text>
</string>
<string id="ui_exp_UI_title">
    <text>Nastavení UI</text>
</string>

<string id="ui_exp_UI_general_ui_option_title">
    <text>Obecné</text>
</string>
<string id="ui_exp_UI_OPEN_UI_ANIMATION">
    <text>Animace otevírání UI</text>
</string>
<string id="ui_exp_UI_SHOW_ALL_SKILLS">
    <text>Zobrazit všechny dovednosti</text>
</string>
<string id="ui_exp_UI_SHOW_ALL_SKILLS_desc">
    <text>Zobrazit všechny dostupné dovednosti v seznamu dovedností. Pokud je tato monost zakázána, zobrazí se pouze nauèené dovednosti nebo ty, které mùete nauèit na vaší aktuální úrovni postavy a prestii.</text>
</string>
<string id="ui_exp_UI_SKILL_LEARN_DELAY">
    <text>Zpodìní uèení dovedností</text>
</string>
<string id="ui_exp_UI_UI_SOUND_VOLUME">
    <text>Hlasitost zvukù menu</text>
</string>
<string id="ui_exp_UI_MENU_MUSIC_VOLUME">
    <text>Hlasitost hudby menu</text>
</string>
<string id="ui_exp_UI_MENU_MUSIC_TRACK">
    <text>Hudba na pozadí</text>
</string>

<string id="ui_exp_UI_alerts_title">
    <text>Nastavení upozornìní</text>
</string>
<string id="ui_exp_UI_ALERTS_TYPE">
    <text>Zpùsob upozornìní</text>
</string>
<string id="ui_exp_UI_ALERTS_TYPE_desc">
    <text>Standardní: Upozornìní budou zobrazena prostøednictvím standardního nástroje pro vıstup zpráv. \n \nAPM: (Vyaduje mod "Anomaly Popup Messages"!) Upozornìní budou zobrazena pomocí modu Anomaly Popup Messages. \nPOZNÁMKA: Pokud je toto nastavení vybráno, ale APM není nainstalováno, upozornìní budou vydána standardním zpùsobem.</text>
</string>
<string id="ui_exp_UI_ALERTS_TYPE_DEF">
    <text>Standardní</text>
</string>
<string id="ui_exp_UI_ALERTS_TYPE_APM">
    <text>APM</text>
</string>
<string id="ui_exp_UI_ENABLE_XP_ALERTS">
    <text>Povolit upozornìní na získávání zkušeností</text>
</string>
<string id="ui_exp_UI_XP_ALERTS_VOLUME">
    <text>Hlasitost zvuku získávání zkušeností</text>
</string>
<string id="ui_exp_UI_XP_ALERTS_SOUND">
    <text>Zvuk získávání zkušeností</text>
</string>
<string id="ui_exp_UI_ENABLE_LVLUP_ALERTS">
    <text>Povolit upozornìní na dosaení nové úrovnì</text>
</string>
<string id="ui_exp_UI_LVLUP_ALERTS_VOLUME">
    <text>Hlasitost zvuku dosaení nové úrovnì</text>
</string>
<string id="ui_exp_UI_LVLUP_ALERTS_SOUND">
    <text>Zvuk dosaení nové úrovnì</text>
</string>



<!--

	Options Tasks

-->
	<string id="ui_exp_menu_Tasks">
    <text>Úkoly</text>
</string>

<string id="ui_exp_Tasks_title">
    <text>Nastavení úkolù</text>
</string>
<string id="ui_exp_Tasks_tasks_desc">
    <text>Úkoly vám umoní získat dodateèné peníze nebo zkušenosti. \n \nPOZNÁMKA: S kadım prestiním úrovní se zvıší poèet úkolù, jejich obtínost a odmìna za jejich splnìní. Proto upravte nastavení uvedená níe na základì této podmínky.</text>
</string>

<string id="ui_exp_Tasks_ENABLE_TASKS">
    <text>Povolit úkoly</text>
</string>
<string id="ui_exp_Tasks_SEND_NEWS">
    <text>Povolit oznámení</text>
</string>
<string id="ui_exp_Tasks_SEND_NEWS_desc">
    <text>Povolit oznámení o aktualizaci úkolù nebo o jejich dokonèení.</text>
</string>
<string id="ui_exp_Tasks_AUTOCOMPLETE">
    <text>Povolit automatické dokonèení úkolù</text>
</string>
<string id="ui_exp_Tasks_REFRESH_TIME">
    <text>Èas aktualizace úkolù (v herních hodinách)</text>
</string>
<string id="ui_exp_Tasks_REWARDS_TYPE">
    <text>Typ odmìny</text>
</string>
<string id="ui_exp_Tasks_REWARDS_TYPE_desc">
    <text>Zmìny budou provedeny a po aktualizaci úkolù.</text>
</string>
<string id="ui_exp_Tasks_REWARDS_TYPE_ALL">
    <text>Peníze nebo zkušenosti</text>
</string>
<string id="ui_exp_Tasks_REWARDS_TYPE_MONEY">
    <text>Pouze peníze</text>
</string>
<string id="ui_exp_Tasks_REWARDS_TYPE_EXP">
    <text>Pouze zkušenosti</text>
</string>
<string id="ui_exp_Tasks_FORCE_REFRESH">
    <text>Vynutit aktualizaci úkolù</text>
</string>

	
<string id="ui_exp_Tasks_tasks_options_title">
    <text>Nastavení odmìn</text>
</string>
<string id="ui_exp_Tasks_tasks_options_desc">
    <text>POZNÁMKA: \n \n - Základní peníze jsou násobeny poètem poadovanıch cílù pro dokonèení úkolu. \n - Základní zkušenosti jsou násobeny poètem poadovanıch cílù pro dokonèení úkolu a "Globálním multiplikátorem zkušeností".</text>
</string>

<string id="ui_exp_Tasks_TASK_REWARD_MONEY">
    <text>Základní peníze</text>
</string>
<string id="ui_exp_Tasks_TASK_REWARD_EXP">
    <text>Základní XP</text>
</string>
<string id="ui_exp_Tasks_kill_stalkers_reward_title">
    <text>Úkol: Zabij Stalkery</text>
</string>
<string id="ui_exp_Tasks_kill_mutants_reward_title">
    <text>Úkol: Zabij Mutanty</text>
</string>
<string id="ui_exp_Tasks_find_stashes_reward_title">
    <text>Úkol: Najdi skrıše</text>
</string>
<string id="ui_exp_Tasks_find_artefacts_reward_title">
    <text>Úkol: Najdi artefakty</text>
</string>
<string id="ui_exp_Tasks_complete_tasks_reward_title">
    <text>Úkol: Dokonèit úkoly</text>
</string>
<string id="ui_exp_Tasks_craft_items_reward_title">
    <text>Úkol: Vyrobit pøedmìty</text>
</string>
<string id="ui_exp_Tasks_cooking_foods_reward_title">
    <text>Úkol: Uvaøit jídlo</text>
</string>
<string id="ui_exp_Tasks_kill_gigant_reward_title">
    <text>Úkol: Zabít Pseudogiganta</text>
</string>
<string id="ui_exp_Tasks_kill_chimera_reward_title">
    <text>Úkol: Zabít Chiméru</text>
</string>
<string id="ui_exp_Tasks_kill_burer_reward_title">
    <text>Úkol: Zabít Trpaslíka</text>
</string>
<string id="ui_exp_Tasks_kill_poltergeist_reward_title">
    <text>Úkol: Zabít Poltergeista</text>
</string>
<string id="ui_exp_Tasks_kill_exp_stalkers_reward_title">
    <text>Úkol: Zabít Stalkera s rankem "Zkušenı" nebo vyšším</text>
</string>
<string id="ui_exp_Tasks_kill_zombie_reward_title">
    <text>Úkol: Zabít Zombie</text>
</string>
<string id="ui_exp_Tasks_kill_controller_reward_title">
    <text>Úkol: Zabít Kontroléra</text>
</string>
<string id="ui_exp_Tasks_disassembly_items_reward_title">
    <text>Úkol: Demontovat pøedmìt</text>
</string>
<string id="ui_exp_Tasks_repair_items_reward_title">
    <text>Úkol: Opravit pøedmìt</text>
</string>
<string id="ui_exp_Tasks_looting_mutants_reward_title">
    <text>Úkol: Získat èásti mutantù</text>
</string>
<string id="ui_exp_Tasks_kill_high_level_stalkers_reward_title">
    <text>Úkol: Zabij Stalkery úrovnì 45 a vıše</text>
</string>
<string id="ui_exp_Tasks_kill_high_level_mutants_reward_title">
    <text>Úkol: Zabíj Mutanty úrovnì 45 a vıše</text>
</string>



<!--

	Options NPC LEVELING SYSTEM (NLS)

-->
	<string id="ui_exp_menu_NLS">
    <text>NLS</text>
</string>

<string id="ui_exp_NLS_title">
    <text>Systém úrovnì NPC</text>
</string>
<string id="ui_exp_NLS_diff_level_desc">
    <text>FORMULE MULTIPLIKÁTORU ÚROVNÌ:\n(ROZDÍL V ÚROVNÍCH / PRÁH ROZDÍLU) * MULTIPLIKÁTOR ÚROVNÌ = KONEÈNİ MULTIPLIKÁTOR</text>
</string>
<string id="ui_exp_NLS_DIFF_LEVEL_STAGE">
    <text>Práh rozdílu (v úrovních)</text>
</string>
<string id="ui_exp_NLS_DIFF_LEVEL_STAGE_desc">
    <text>Práh rozdílu v úrovních mezi NPC, pro zmìnu multiplikátorù úrovnì.</text>
</string>
<string id="ui_exp_NLS_ENABLE_EXP_SYS">
    <text>Multiplikátor úrovnì zkušeností pro hráèe</text>
</string>
<string id="ui_exp_NLS_ENABLE_EXP_SYS_desc">
    <text>Povolit multiplikátor úrovnì zkušeností za zabití NPC pro hráèe (multiplikátory ranku budou ignorovány).</text>
</string>
<string id="ui_exp_NLS_DIFF_LEVEL_STAGE_EXP_MULT">
    <text>Multiplikátor úrovnì zkušeností</text>
</string>
<string id="ui_exp_NLS_ENABLE_DMG_SYS">
    <text>Multiplikátor úrovnì poškození pro hráèe a NPC</text>
</string>
<string id="ui_exp_NLS_ENABLE_DMG_SYS_desc">
    <text>Povolit multiplikátor úrovnì poškození pro NPC a hráèe.</text>
</string>
<string id="ui_exp_NLS_DIFF_LEVEL_STAGE_DMG_MULT">
    <text>Multiplikátor úrovnì poškození</text>
</string>

<string id="ui_exp_NLS_ENABLE_TARGET_HUD">
    <text>Zobrazit HUD npc levelù</text>
</string>
<string id="ui_exp_NLS_SHOW_FAKE_HEALTH">
    <text>HUD NPC: Èíselné zdraví npc</text>
</string>
<string id="ui_exp_NLS_SHOW_FAKE_HEALTH_desc">
    <text>Zobrazit èíselné (falešné) hodnoty zdraví cíle místo procent.</text>
</string>
<string id="ui_exp_NLS_HUD_FADE_TIME">
    <text>HUD NPC: Èas ztráty</text>
</string>
<string id="ui_exp_NLS_TARGET_HUD_DISPLAY_MODE">
    <text>HUD NPC: Reim zobrazení</text>
</string>
<string id="ui_exp_NLS_TARGET_HUD_DISPLAY_MODE_always">
    <text>Vdy</text>
</string>
<string id="ui_exp_NLS_TARGET_HUD_DISPLAY_MODE_combat">
    <text>Pouze v boji</text>
</string>
<string id="ui_exp_NLS_TARGET_HUD_NAME_MODE">
    <text>HUD NPC: Reim zobrazení jmén</text>
</string>
<string id="ui_exp_NLS_TARGET_HUD_NAME_MODE_none">
    <text>Nezobrazovat</text>
</string>
<string id="ui_exp_NLS_TARGET_HUD_NAME_MODE_name">
    <text>Pouze jméno</text>
</string>
<string id="ui_exp_NLS_TARGET_HUD_NAME_MODE_lvl">
    <text>Pouze úroveò</text>
</string>
<string id="ui_exp_NLS_TARGET_HUD_NAME_MODE_lvlname">
    <text>Úroveò a jméno</text>
</string>
<string id="ui_exp_NLS_hud_position_desc">
    <text>
    Ovládání:
    \n - LPM: zmìnit pozici HUD
    \n - ENTER: uloit zmìny
    \n - ESCAPE: vrátit zmìny zpìt
    </text>
</string>
<string id="ui_exp_NLS_CHANGE_POSITION">
    <text>Zmìnit pozici HUD</text>
</string>
<string id="ui_exp_NLS_RESET_POSITION">
    <text>Resetovat pozici HUD</text>
</string>

<string id="ui_exp_NLS_locations_desc">
    <text>
    Níe jsou nastavení související s základními úrovnìmi NPC, které obdrí pøi inicializaci v Zónì, v závislosti na lokaci.
    \nÚroveò NPC je náhodnì vybrána v urèeném rozsahu urèité lokace.\n 
    \nPOZNÁMKA: Úroveò NPC nemùe bıt vyšší ne maximální moná úroveò postavy.
    </text>
</string>
<string id="ui_exp_NLS_level_loc_min">
    <text>Min. základní úroveò</text>
</string>
<string id="ui_exp_NLS_level_loc_max">
    <text>Max. základní úroveò</text>
</string>

<string id="ui_st_experience_nls_target_bar_level">
    <text>%s úroveò</text>
</string>



<!--

	Options IRONMAN ROGUELITE

-->
	<string id="ui_exp_IronmanRoguelite_not_installed">
    <text>Mod "Jabbers Ironman Roguelite" není nainstalován.</text>
</string>
<string id="ui_exp_menu_IronmanRoguelite">
    <text>Ironman Roguelite</text>
</string>

<string id="ui_exp_IronmanRoguelite_title">
    <text>Ironman Roguelite</text>
</string>
<string id="ui_exp_IronmanRoguelite_desc">
    <text>Systém pøenášení pokroku pøi levelování postavy v reimu "Ironman" s vyuitím módu "Jabbers Ironman Roguelite".\n \nPOZNÁMKA: Pøi hraní v reimu "Azazel", pokud máte nainstalován doplnìk "Experience Azazel" a monost "Azazel: Novı pokrok" z sekce "Hlavní" je povolena, pak se pokrok obnovovat nebude.</text>
</string>
<string id="ui_exp_IronmanRoguelite_TRANSFER_PROGRESS">
    <text>Povolit pøenos pokroku v levelování</text>
</string>
<string id="ui_exp_IronmanRoguelite_RESTORE_SKILLS">
    <text>Uèit dovednosti</text>
</string>
<string id="ui_exp_IronmanRoguelite_RESTORE_SKILLS_desc">
    <text>Uèit dovednosti z minulého prùchodu, pokud je to moné.</text>
</string>
<string id="ui_exp_IronmanRoguelite_LOSS_PROGRESS">
    <text>Ztráta pokroku v levelování</text>
</string>
<string id="ui_exp_IronmanRoguelite_LOSS_PROGRESS_desc">
    <text>Ztráta pokroku v levelování z posledního prùchodu.</text>
</string>
	<string id="ui_exp_IronmanRoguelite_RESTORE_TRAITS">
		<text>Obnovení traitù</text>
	</string>

<!--

	MAIN MENU UI

-->
	<string id="ui_st_experience_main_wnd_btn_hint_skills">
    <text>Menu dovedností</text>
</string>
<string id="ui_st_experience_main_wnd_btn_hint_tasks">
    <text>Menu úkolù</text>
</string>
<string id="ui_st_experience_main_wnd_btn_hint_options">
    <text>Menu informací a nastavení</text>
</string>
<string id="ui_st_experience_main_wnd_btn_hint_xpmult">
    <text>Menu multiplikátorù zkušeností</text>
</string>
<string id="ui_st_experience_main_wnd_btn_hint_debug">
    <text>Menu konzole</text>
</string>
<string id="ui_st_experience_main_wnd_actor_level_hint">
    <text>Maximální úroveò: %s \nCelková zkušenost: %s XP</text>
</string>
<string id="ui_st_experience_main_wnd_actor_prestige_hint">
    <text>Maximální prestiní úroveò: %s</text>
</string>
<string id="ui_st_experience_main_wnd_actor_skillpoints_hint">
    <text>Dovednostní body na úroveò: %s</text>
</string>

<string id="ui_st_experience_main_wnd_actor_level">
    <text>ÚROVEÒ</text>
</string>
<string id="ui_st_experience_main_wnd_actor_prestige">
    <text>PRESTI</text>
</string>
<string id="ui_st_experience_main_wnd_actor_skillpoints">
    <text>DOVEDNOSTNÍ BODY:</text>
</string>

<string id="ui_st_experience_main_wnd_inc_prestige_description">
    <text>%c[d_orange]Zvıšení prestie zvıší vaši maximální úroveò o %s, zvıší dobu úèinnosti "Vìdeckı lektvar" a pravdìpodobnost jejich nalezení. Úkolù bude také více, jejich obtínost a odmìna za jejich dokonèení se zvıší. \n \n%c[d_green]Zvıšit presti na úroveò %s?</text>
</string>
<string id="ui_st_experience_main_wnd_inc_prestige_done_msg">
    <text>Presti byla zvıšena na úroveò %s!</text>
</string>

<string id="ui_experience_options_btn_accept">
    <text>Uloit</text>
</string>
<string id="ui_experience_options_btn_default">
    <text>Vıchozí</text>
</string>
<string id="ui_experience_options_btn_cancel">
    <text>Zrušit</text>
</string>
<string id="ui_experience_options_presets">
    <text>Pøednastavení</text>
</string>
<string id="ui_experience_options_warning_pending">
    <text>Máš (%s) neuloenıch zmìn.</text>
</string>
<string id="ui_experience_options_change_done">
    <text>Zmìny jsou uloeny</text>
</string>
<string id="ui_experience_options_tasks_reloaded">
    <text>Úkoly byly aktualizovány</text>
</string>



<!--

	TASKS MENU UI

-->
<string id="ui_experience_tasks_wnd_reward_cap">
    <text>Odmìna:</text>
</string>
<string id="ui_experience_tasks_wnd_task_completed">
    <text>DOPLNÌNO</text>
</string>
<string id="ui_experience_tasks_btn_complete_task">
    <text>Dokonèit</text>
</string>
<string id="ui_experience_tasks_wnd_timer_cap">
    <text>Obnovení za:</text>
</string>
<string id="ui_experience_tasks_wnd_timer_hours">
    <text>hod.</text>
</string>
<string id="ui_experience_tasks_wnd_timer_minutes">
    <text>min.</text>
</string>
<string id="ui_experience_tasks_wnd_tasks_disabled">
    <text>Úkoly jsou vypnuty</text>
</string>
<string id="ui_experience_tasks_wnd_task_completed_msg">
    <text>Úkol "%s" byl dokonèen! \n%s</text>
</string>



<!--

	SKILLS MENU UI

-->
	<string id="ui_experience_skills_wnd_skill_name_lvl">
    <text>(úroveò %s)</text>
</string>
<string id="ui_experience_skills_wnd_skill_name_lvlmax">
    <text>(Max.)</text>
</string>
<string id="ui_experience_skills_wnd_selected_lvl">
    <text>Úroveò %s</text>
</string>
<string id="ui_experience_skills_wnd_selected_prev_lvl">
    <text>(Ji nauèeno)</text>
</string>
<string id="ui_experience_skills_wnd_selected_curr_lvl">
    <text>(Aktuální úroveò)</text>
</string>
<string id="ui_experience_skills_wnd_selected_next_lvl">
    <text>(Vyaduje úroveò %s)</text>
</string>
<string id="ui_experience_skills_wnd_skill_tip_can_learn">
    <text>[E] Nauèit se</text>
</string>
<string id="ui_experience_skills_wnd_skill_tip_max_level">
    <text>Dosaen maximální úroveò</text>
</string>
<string id="ui_experience_skills_wnd_skill_tip_not_have_skillpoints">
    <text>Nedostatek bodù dovedností</text>
</string>
<string id="ui_experience_skills_wnd_skill_tip_neded_actor_level">
    <text>Vyaduje úroveò %s</text>
</string>
<string id="ui_experience_skills_wnd_skill_tip_neded_prestige_level">
    <text>Vyaduje prestiní úroveò %s</text>
</string>
<string id="ui_experience_skills_wnd_skill_tip_process_learn">
    <text>Uèí se...</text>
</string>

<string id="ui_experience_skills_wnd_skill_search_skill_cap">
    <text>Hledat</text>
</string>
<string id="ui_experience_skills_wnd_skill_hide_learned_skills_cap">
    <text>Skrıt nauèené dovednosti</text>
</string>
<string id="ui_experience_skills_wnd_skill_edit_mode_cap">
    <text>Reim úpravy</text>
</string>
<string id="ui_experience_skills_wnd_skill_sort_list_cap">
    <text>Zpùsob øazení</text>
</string>
<string id="ui_experience_skills_wnd_skill_sort_list_1">
    <text>Abecednì (A a Z)</text>
</string>
<string id="ui_experience_skills_wnd_skill_sort_list_2">
    <text>Abecednì (Z a A)</text>
</string>
<string id="ui_experience_skills_wnd_skill_sort_list_3">
    <text>Podle maximální vyadované úrovnì</text>
</string>
<string id="ui_experience_skills_wnd_skill_sort_list_4">
    <text>Podle aktuální vyadované úrovnì</text>
</string>
<string id="ui_experience_skills_wnd_skill_category_all">
    <text>Vše</text>
</string>
<string id="ui_experience_skills_wnd_skill_category_misc">
    <text>Rùzné</text>
</string>
<string id="ui_experience_skills_wnd_skill_category_no_loaded_skills">
    <text>Dovednosti nebyly nalezeny!</text>
</string>

	
	<!-- Editor Mode -->
<string id="ui_experience_skills_wnd_edit_mode_btn_save">
    <text>Uloit</text>
</string>
<string id="ui_experience_skills_wnd_edit_mode_btn_reset">
    <text>Vıchozí</text>
</string>
<string id="ui_experience_skills_wnd_edit_mode_req_level_name">
    <text>Min. poadovaná úroveò</text>
</string>
<string id="ui_experience_skills_wnd_edit_mode_each_level_name">
    <text>Krok úrovní</text>
</string>
<string id="ui_experience_skills_wnd_edit_mode_req_prestige_name">
    <text>Min. poadovaná presti</text>
</string>



<!--

	EXPERIENCE MULTIPLIERS MENU UI

-->
<string id="ui_experience_xpmult_wnd_mult_killed_npc">
    <text>Zabití stalkerù</text>
</string>
<string id="ui_experience_xpmult_wnd_mult_killed_mutant">
    <text>Zabití mutantù</text>
</string>
<string id="ui_experience_xpmult_wnd_mult_task_completed">
    <text>Plnìní úkolù</text>
</string>
<string id="ui_experience_xpmult_wnd_mult_finded_stash">
    <text>Nalezení úkrytù</text>
</string>
<string id="ui_experience_xpmult_wnd_mult_discovered_spot">
    <text>Objevování míst</text>
</string>
<string id="ui_experience_xpmult_wnd_mult_disassemble_item">
    <text>Rozbírání pøedmìtù</text>
</string>
<string id="ui_experience_xpmult_wnd_mult_looted_mutant">
    <text>Šití mutantù</text>
</string>
<string id="ui_experience_xpmult_wnd_mult_repaired_item">
    <text>Opravování pøedmìtù</text>
</string>
<string id="ui_experience_xpmult_wnd_mult_cooking">
    <text>Vaøení</text>
</string>
<string id="ui_experience_xpmult_wnd_mult_workshop">
    <text>Práce na pracovním stolu</text>
</string>
<string id="ui_experience_xpmult_wnd_mult_finded_artefact">
    <text>Nalezení artefaktù</text>
</string>
<string id="ui_experience_xpmult_wnd_mult_haru_skill_up">
    <text>Úrovnì dovedností z módu "Anomaly Skill System"</text>
</string>
<string id="ui_experience_xpmult_wnd_bonus_global_mult">
    <text>Celkovı násobitel</text>
</string>
<string id="ui_experience_xpmult_wnd_bonus_potions_mult">
    <text>Násobitel lektvarù</text>
</string>
<string id="ui_experience_xpmult_wnd_bonus_location_mult">
    <text>Násobitel lokace:</text>
</string>





<!--

	TRAITS MENU UI

-->
<string id="ui_experience_traits_wnd_trait_slot_need_prestige">
    <text>Vyaduje prestiní úroveò %s</text>
</string>
<string id="ui_experience_traits_wnd_trait_upgrade_mode_1">
    <text>Upgrade</text>
</string>
<string id="ui_experience_traits_wnd_trait_inc_quality_mode_1">
    <text>Zlepšit kvalitu</text>
</string>
<string id="ui_experience_traits_wnd_trait_upgrade_mode_2">
    <text>Upgrade na +%s (Šance: %s%)</text>
</string>
<string id="ui_experience_traits_wnd_trait_destroy_mode_1">
    <text>Znièit (+%s XP)</text>
</string>
<string id="ui_experience_traits_wnd_trait_destroy_mode_2">
    <text>Zpìt</text>
</string>
<string id="ui_experience_traits_wnd_trait_warning_msg_on_upgrade">
    <text>%c[d_orange]VAROVÁNÍ: \n \nOpravdu chcete provést upgrade s trait na vysoké úrovni? Trait bude ztracen!</text>
</string>
<string id="ui_experience_traits_wnd_trait_warning_msg_on_destroy">
    <text>%c[d_orange]Jste si jisti?</text>
</string>
<string id="ui_experience_traits_wnd_trait_warning_msg_inc_quality">
    <text>%c[d_orange]Zlepšení kvality trait zvıší jeho úèinky pro kadou úroveò, ale jeho aktuální úroveò klesne na +1.\n \n%c[d_green]Chcete zlepšit kvalitu trait?</text>
</string>
<string id="ui_experience_traits_wnd_replace_trait_hint">
    <text>Nahradit s:</text>
</string>

<string id="ui_experience_traits_wnd_upgrade_trait_success_msg">
    <text>Zvıšeno: "%s" na +%s!</text>
</string>
<string id="ui_experience_traits_wnd_upgrade_trait_fail_msg">
    <text>Neuspìšné!</text>
</string>
<string id="ui_experience_traits_wnd_trait_quality_name">
    <text>%c[d_blue] • %c[default]Kvalita:</text>
</string>
<string id="ui_experience_traits_wnd_trait_quality_very_bad">
    <text>%c[255,210,20,20]Hrozná</text>
</string>
<string id="ui_experience_traits_wnd_trait_quality_bad">
    <text>%c[255,205,205,205]Špatná</text>
</string>
<string id="ui_experience_traits_wnd_trait_quality_normal">
    <text>%c[255,100,220,140]Bìná</text>
</string>
<string id="ui_experience_traits_wnd_trait_quality_good">
    <text>%c[255,35,110,175]Dobrá</text>
</string>
<string id="ui_experience_traits_wnd_trait_quality_epic">
    <text>%c[255,180,65,240]Epická</text>
</string>
<string id="ui_experience_traits_wnd_trait_quality_legendary">
    <text>%c[255,240,195,40]Legendární</text>
</string>
<string id="ui_experience_traits_wnd_trait_quality_mythic">
    <text>%c[255,240,100,40]Mystická</text>
</string>
<string id="ui_experience_traits_wnd_trait_inc_quality_bad_msg">
    <text>%c[255,205,205,205]"%s" zlepšeno na kvalitu "Špatná"!</text>
</string>
<string id="ui_experience_traits_wnd_trait_inc_quality_normal_msg">
    <text>%c[255,100,220,140]"%s" zlepšeno na kvalitu "Bìná"!</text>
</string>
<string id="ui_experience_traits_wnd_trait_inc_quality_good_msg">
    <text>%c[255,35,110,175]"%s" zlepšeno na kvalitu "Dobrá"!</text>
</string>
<string id="ui_experience_traits_wnd_trait_inc_quality_epic_msg">
    <text>%c[255,180,65,240]"%s" zlepšeno na kvalitu "Epická"!</text>
</string>

	<string id="ui_experience_traits_wnd_trait_inc_quality_legendary_msg">
    <text>%c[255,240,195,40]"%s" zlepšeno na kvalitu "Legendární"!</text>
</string>
<string id="ui_experience_traits_wnd_trait_inc_quality_mythic_msg">
    <text>%c[255,240,100,40]"%s" zlepšeno na kvalitu "Mystická"!</text>
</string>




<!--

	XP GAIN AND LEVEL UP ALERTS

-->
	<string id="st_xp_alert_gain_xp_cap">
    <text>Navıšení zkušeností!</text>
</string>
<string id="st_xp_alert_gain_xp_text_def">
    <text>%sZískáno: +%s XP</text>
</string>
<string id="st_xp_alert_gain_xp_text_apm">
    <text>Získáno: +%s XP</text>
</string>

<string id="st_xp_alert_levelup_cap">
    <text>Získan level!</text>
</string>
<string id="st_xp_alert_levelup_text_def">
    <text>%sDosaenı level: %s \nDostupné body dovedností: %s</text>
</string>
<string id="st_xp_alert_levelup_text_apm">
    <text>Dosaenı level: %s Dostupné body dovedností: %s</text>
</string>



<!--

	POTIONS

-->
<string id="st_xp_menu_potion_drink">
    <text>Vypít</text>
</string>
<string id="st_xp_you_have_oblivion_potion_debuff_msg">
    <text>Máš negativní efekt "Lektvar zapomnìní"</text>
</string>
<string id="st_xp_you_have_oblivion_potion_debuff_death_msg">
    <text>Nemohl jste vydret negativní efekt...</text>
</string>
<string id="st_xp_unknown_experience_potion_msg">
    <text>Zkoušíte vypít nìco špatného...</text>
</string>
<string id="st_xp_experience_potion_greater_effect_msg">
    <text>Ji jste ovlivnìni silnìjším lektvarem</text>
</string>

<string id="st_xp_oblivion_potion_name">
    <text>Lektvar zapomnìní</text>
</string>
<string id="st_xp_oblivion_potion_descr">
    <text>Není známo, kdo tento lektvar vyrábí a z èeho se skládá, ale zápach je odpornı...\n \n
    %c[ui_gray_3]VLASTNOSTI:\n
    %c[d_blue] • %c[ui_gray_2] lektvar\n
    %c[d_cyan] • %c[ui_gray_2] umoòuje zapomenout na všechny nauèené dovednosti\n
    %c[d_red] • %c[ui_gray_2] doèasnì sniuje získávané zkušenosti o 50% ze všech zdrojù\n
    %c[d_red] • %c[ui_gray_2] bìhem úèinku nemùete pouívat jiné lektvary\n
    %c[d_red] • %c[ui_gray_2] bìhem úèinku bude opìtovné pouití smrtící\n
    %c[d_blue] • %c[ui_gray_2] trvání: 600 sekund\n
    </text>
</string>

<string id="st_xp_experience_potion_buff_descr">
    <text>Není známo, kdo tento lektvar vyrábí a z èeho se skládá, ale zdá se, e voní jako tøešnì.\n \n
    %c[ui_gray_3]VLASTNOSTI:\n
    %c[d_blue] • %c[ui_gray_2] lektvar\n
    %c[d_green] • %c[ui_gray_2] doèasnì zvyšuje získávané zkušenosti ze všech zdrojù\n
    %c[d_blue] • %c[ui_gray_2] trvání: %s sekund\n
    </text>
</string>
<string id="st_xp_experience_potion_buff_10_name">
    <text>Vìdeckı lektvar (10%)</text>
</string>
<string id="st_xp_experience_potion_buff_25_name">
    <text>Vìdeckı lektvar (25%)</text>
</string>
<string id="st_xp_experience_potion_buff_50_name">
    <text>Vìdeckı lektvar (50%)</text>
</string>
<string id="st_xp_experience_potion_buff_75_name">
    <text>Vìdeckı lektvar (75%)</text>
</string>
<string id="st_xp_experience_potion_buff_100_name">
    <text>Vìdeckı lektvar (100%)</text>
</string>
<string id="st_xp_experience_potion_buff_150_name">
    <text>Vìdeckı lektvar (150%)</text>
</string>

	
	<string id="st_xp_experience_potion_name">
		<text>Vìdeckı lektvar</text>
	</string>
	<string id="st_xp_experience_potion_descr">
		<text>Není známo, kdo tento lektvar vyrábí a z èeho se skládá, ale zdá se, e voní po tøešních.\n \n
		%c[ui_gray_3]VLASTNOSTI:\n
		%c[d_blue] - %c[ui_gray_2] lektvar\n
		%c[d_cyan] - %c[ui_gray_2] dává zkušenosti\n
		</text>
	</string>



 <!-- Traity -->
	<string id="st_xp_trait_desc_header">
		<text>%c[d_orange] - %c[ui_gray_1]Vazba na take\n \n</text>
	</string>
	<string id="st_xp_trait_gems_generic_desc">
		<text>Drahı kámen, kterı nachází vyuití jako šperk a okrasná surovina.\n \n
		%c[ui_gray_3]VLASTNOSTI:\n
		%c[d_blue] - %c[ui_gray_2] drahokam\n
		%c[d_cyan] - %c[ui_gray_2] pouívá se jako vlastnost v menu Zkušenosti\n
		</text>
	</string>
	<string id="st_xp_trait_amethyst_name">
		<text>Ametystovı úlomek</text>
	</string>
	<string id="st_xp_trait_lazurite_name">
		<text>Lazuritovı úlomek</text>
	</string>
	<string id="st_xp_trait_turquoise_name">
		<text>Turkızovı úlomek</text>
	</string>
	<string id="st_xp_trait_emerald_name">
		<text>Emeraldovı støep</text>
	</string>
	<string id="st_xp_trait_topaz_name">
		<text>Topaz støep</text>
	</string>
	<string id="st_xp_trait_agate_name">
		<text>Agate shard</text>
	</string>
	<string id="st_xp_trait_nephrite_name">
		<text>Nefritovı støep</text>
	</string>
	<string id="st_xp_trait_diamond_name">
		<text>Diamantovı úlomek</text>
	</string>
	<string id="st_xp_trait_aqua_name">
		<text>Akvamarínovı úlomek</text>
	</string>
	<string id="st_xp_trait_tsavorite_name">
		<text>Tsavoritovı úlomek</text>
	</string>
	<string id="st_xp_trait_alexandrite_name">
		<text>Alexandritovı úlomek</text>
	</string>
	
	<string id="st_xp_trait_bonus_descr">
		<text>%c[d_blue] - %c[default]Zvyšuje získané zkušenosti o %s% pro:\n</text>
	</string>

Translated with www.DeepL.com/Translator (free version)

<!--

	TASKS MANAGER

-->
<string id="st_xp_tasks_manager_kill_stalkers_name">
    <text>Zabij stalkerù</text>
</string>
<string id="st_xp_tasks_manager_kill_mutants_name">
    <text>Zabij mutanti</text>
</string>
<string id="st_xp_tasks_manager_find_stashes_name">
    <text>Najdi úkryty</text>
</string>
<string id="st_xp_tasks_manager_find_artefacts_name">
    <text>Najdi artefakty</text>
</string>
<string id="st_xp_tasks_manager_complete_tasks_name">
    <text>Dokonèi úkoly</text>
</string>
<string id="st_xp_tasks_manager_craft_items_name">
    <text>Vytvoø pøedmìty</text>
</string>
<string id="st_xp_tasks_manager_cooking_foods_name">
    <text>Uvaø jídlo</text>
</string>
<string id="st_xp_tasks_manager_kill_gigant_name">
    <text>Zabij pseudogiganta</text>
</string>
<string id="st_xp_tasks_manager_kill_chimera_name">
    <text>Zabij chimeru</text>
</string>
<string id="st_xp_tasks_manager_kill_burer_name">
    <text>Zabij burera</text>
</string>
<string id="st_xp_tasks_manager_kill_poltergeist_name">
    <text>Zabij poltergeista</text>
</string>
<string id="st_xp_tasks_manager_kill_exp_stalkers_name">
    <text>Zabij stalkerù s hodností "Zkušenı" nebo vyšší</text>
</string>
<string id="st_xp_tasks_manager_kill_zombie_name">
    <text>Zabij zombie</text>
</string>
<string id="st_xp_tasks_manager_kill_controller_name">
    <text>Zabij Kontrolora</text>
</string>
<string id="st_xp_tasks_manager_disassembly_items_name">
    <text>Demontuj pøedmìty</text>
</string>
<string id="st_xp_tasks_manager_repair_items_name">
    <text>Oprav pøedmìty</text>
</string>
<string id="st_xp_tasks_manager_looting_mutants_name">
    <text>Seber èásti mutantù</text>
</string>
<string id="st_xp_tasks_manager_kill_high_level_stalkers_name">
    <text>Zabij stalkery úrovnì 45 nebo vyšší</text>
</string>
<string id="st_xp_tasks_manager_kill_high_level_mutants_name">
    <text>Zabij mutanty úrovnì 45 nebo vyšší</text>
</string>

	
	<string id="st_xp_tasks_manager_news_refresh_msg">
    <text>%c[d_orange]Experience Framework: %c[d_green]Úkoly aktualizovány!</text>
</string>
<string id="st_xp_tasks_manager_news_task_done_msg">
    <text>%c[d_orange]Experience Framework: %c[d_green]Úkol «%s» - cíl dosaen!</text>
</string>
<string id="st_xp_tasks_manager_news_task_completed_msg">
    <text>%c[d_orange]Experience Framework: %c[d_green]Úkol «%s» je dokonèen! \n - Odmìna: %s</text>
</string>



<!--

	OPTIONS HINT LOCATIONS

-->
	<string id="ui_exp_options_hint_fake_start">
    <text>Falešnı zaèátek</text>
</string>
<string id="ui_exp_options_hint_k00_marsh">
    <text>Velké bainy</text>
</string>
<string id="ui_exp_options_hint_l01_escape">
    <text>Kordon</text>
</string>
<string id="ui_exp_options_hint_k01_darkscape">
    <text>Darkscape</text>
</string>
<string id="ui_exp_options_hint_y04_pole">
    <text>Louka</text>
</string>
<string id="ui_exp_options_hint_l02_garbage">
    <text>Smetištì</text>
</string>
<string id="ui_exp_options_hint_l03_agroprom">
    <text>Agroprom</text>
</string>
<string id="ui_exp_options_hint_l04_darkvalley">
    <text>Temné údolí</text>
</string>
<string id="ui_exp_options_hint_l05_bar">
    <text>Rostok</text>
</string>
<string id="ui_exp_options_hint_l06_rostok">
    <text>Divoké území</text>
</string>
<string id="ui_exp_options_hint_k02_trucks_cemetery">
    <text>Høbitov kamionù</text>
</string>
<string id="ui_exp_options_hint_l08_yantar">
    <text>Yantar</text>
</string>
<string id="ui_exp_options_hint_l07_military">
    <text>Armádní sklady</text>
</string>
<string id="ui_exp_options_hint_l09_deadcity">
    <text>Mrtvé mìsto</text>
</string>
<string id="ui_exp_options_hint_l10_red_forest">
    <text>Rudı les</text>
</string>
<string id="ui_exp_options_hint_l10_radar">
    <text>Radar</text>
</string>
<string id="ui_exp_options_hint_l10_limansk">
    <text>Limansk</text>
</string>
<string id="ui_exp_options_hint_l11_pripyat">
    <text>Pripyat</text>
</string>
<string id="ui_exp_options_hint_pripyat">
    <text>Pøedmìstí</text>
</string>
<string id="ui_exp_options_hint_jupiter">
    <text>Jupiter</text>
</string>
<string id="ui_exp_options_hint_zaton">
    <text>Zaton</text>
</string>
<string id="ui_exp_options_hint_l11_hospital">
    <text>Opuštìná nemocnice</text>
</string>
<string id="ui_exp_options_hint_l12_stancia">
    <text>Èernobylská jaderná elektrárna (jih)</text>
</string>
<string id="ui_exp_options_hint_l12_stancia_2">
    <text>Èernobylská jaderná elektrárna (sever)</text>
</string>
<string id="ui_exp_options_hint_l13_generators">
    <text>Generátory</text>
</string>
<string id="ui_exp_options_hint_l03u_agr_underground">
    <text>Podzemí Agropromu</text>
</string>
<string id="ui_exp_options_hint_jupiter_underground">
    <text>Podzemí Jupiteru</text>
</string>
<string id="ui_exp_options_hint_l08u_brainlab">
    <text>Laboratoø X16 (Yantar)</text>
</string>
<string id="ui_exp_options_hint_l04u_labx18">
    <text>Laboratoø X18 (Temné údolí)</text>
</string>
<string id="ui_exp_options_hint_l10u_bunker">
    <text>Laboratoø X19 (Radar)</text>
</string>
<string id="ui_exp_options_hint_labx8">
    <text>Laboratoø X8 (Okolí)</text>
</string>
<string id="ui_exp_options_hint_l12u_control_monolith">
    <text>Centrum kontroly monolitu</text>
</string>
<string id="ui_exp_options_hint_l13u_warlab">
    <text>Vızkumná laboratoø monolitu</text>
</string>
<string id="ui_exp_options_hint_l12u_sarcofag">
    <text>Sarkofág</text>
</string>

	<!-- NEW LEVELS -->
	<string id="ui_exp_options_hint_promzona">
		<text>Promzóna (New Levels Mod)</text>
	</string>
	<string id="ui_exp_options_hint_grimwood">
		<text>Smrèina</text>
	</string>
	<string id="ui_exp_options_hint_poselok_ug">
		<text>Mìsto "Yuzhniy" </text>
	</string>
	<string id="ui_exp_options_hint_bunker_a1">
		<text>Bunkr A1 </text>
	</string>
	<string id="ui_exp_options_hint_collaider">
		<text>Collaider</text>
	</string>



<!--

	ERROR LOADING MESSAGE

-->
<string id="ui_st_experience_framework_incorrect_game_version_msg">
    <text>
    %c[d_cyan]Experience Framework v%s\n
    \n%c[d_red][CHYBA!] Verze hry není kompatibilní s frameworkem.\n%c[d_orange]Aktuální verze hry: %s\n%c[d_green]Poadovaná verze hry: %s\n
    \n%c[ui_gray_3]Aktualizujte verzi hry nebo odstraòte Experience Framework!\n
    \n%c[d_green]STISKNÌTE OK PRO POKRAÈOVÁNÍ
    </text>
</string>


</string_table>